izaber/__init__.py
izaber/compat.py
izaber/date.py
izaber/email.py
izaber/log.py
izaber/paths.py
izaber/startup.py
izaber/structs.py
izaber/templates.py
izaber/zconfig.py
izaber/zdatetime.py
izaber-3.1.20240731.dist-info/WHEEL
izaber-3.1.20240731.dist-info/METADATA
izaber-3.1.20240731.dist-info/RECORD
